[{"id": 90767, "bioguide_id": "N000147", "politician_name": "Eleanor Holmes Norton", "ticker": "BRK/B", "asset_name": "Berkshire Hathaway Inc", "transaction_type": "sale", "transaction_date": "2025-10-14", "disclosure_date": "2025-10-22", "amount_display": "15K\u201350K", "owner": "Undisclosed", "price_at_trade": null, "price_current": null, "return_pct": null, "party": "D", "chamber": "house", "state": "DC", "photo_url": "https://bioguide.congress.gov/bioguide/photo/N/N000147.jpg", "in_office": 1}, {"id": 70550, "bioguide_id": "N000147", "politician_name": "Eleanor Holmes Norton", "ticker": "B", "asset_name": "Berkshire Hathaway IncBRK/", "transaction_type": "sale", "transaction_date": "2025-10-14", "disclosure_date": "", "amount_display": "15K\u201350K", "owner": "Undisclosed", "price_at_trade": null, "price_current": null, "return_pct": null, "party": "D", "chamber": "house", "state": "DC", "photo_url": "https://bioguide.congress.gov/bioguide/photo/N/N000147.jpg", "in_office": 1}, {"id": 100588, "bioguide_id": "N000147", "politician_name": "Eleanor Holmes Norton", "ticker": "BRK/B", "asset_name": "Berkshire Hathaway Inc", "transaction_type": "sale", "transaction_date": "2025-03-05", "disclosure_date": "2025-03-13", "amount_display": "15K\u201350K", "owner": "Undisclosed", "price_at_trade": null, "price_current": null, "return_pct": null, "party": "D", "chamber": "house", "state": "DC", "photo_url": "https://bioguide.congress.gov/bioguide/photo/N/N000147.jpg", "in_office": 1}, {"id": 78437, "bioguide_id": "N000147", "politician_name": "Eleanor Holmes Norton", "ticker": "B", "asset_name": "Berkshire Hathaway IncBRK/", "transaction_type": "sale", "transaction_date": "2025-03-05", "disclosure_date": "", "amount_display": "15K\u201350K", "owner": "Undisclosed", "price_at_trade": null, "price_current": null, "return_pct": null, "party": "D", "chamber": "house", "state": "DC", "photo_url": "https://bioguide.congress.gov/bioguide/photo/N/N000147.jpg", "in_office": 1}, {"id": 61866, "bioguide_id": "UNKNOWN_ELEANOR_HOLMES_NORTONDEMOCRATHOUSEWA", "politician_name": "Eleanor Holmes Norton", "ticker": "B", "asset_name": "Berkshire Hathaway IncBRK/", "transaction_type": "sale", "transaction_date": "2025-03-05", "disclosure_date": "12 Mar2025", "amount_display": "15K\u201350K", "owner": "", "price_at_trade": null, "price_current": null, "return_pct": null, "party": null, "chamber": null, "state": null, "photo_url": null, "in_office": null}, {"id": 106385, "bioguide_id": "N000147", "politician_name": "Eleanor Holmes Norton", "ticker": "BRK/B", "asset_name": "Berkshire Hathaway Inc", "transaction_type": "sale", "transaction_date": "2024-08-27", "disclosure_date": "6 Sept2024", "amount_display": "15K\u201350K", "owner": "Undisclosed", "price_at_trade": null, "price_current": null, "return_pct": null, "party": "D", "chamber": "house", "state": "DC", "photo_url": "https://bioguide.congress.gov/bioguide/photo/N/N000147.jpg", "in_office": 1}, {"id": 83143, "bioguide_id": "N000147", "politician_name": "Eleanor Holmes Norton", "ticker": "B", "asset_name": "Berkshire Hathaway IncBRK/", "transaction_type": "sale", "transaction_date": "2024-08-27", "disclosure_date": "", "amount_display": "15K\u201350K", "owner": "Undisclosed", "price_at_trade": null, "price_current": null, "return_pct": null, "party": "D", "chamber": "house", "state": "DC", "photo_url": "https://bioguide.congress.gov/bioguide/photo/N/N000147.jpg", "in_office": 1}, {"id": 85560, "bioguide_id": "N000147", "politician_name": "Eleanor Holmes Norton", "ticker": "", "asset_name": "DISTRICT OF COLUMBIA WATER AND SEWER AUTHORITY", "transaction_type": "sale", "transaction_date": "2024-05-13", "disclosure_date": "", "amount_display": "15K\u201350K", "owner": "Undisclosed", "price_at_trade": null, "price_current": null, "return_pct": null, "party": "D", "chamber": "house", "state": "DC", "photo_url": "https://bioguide.congress.gov/bioguide/photo/N/N000147.jpg", "in_office": 1}, {"id": 85559, "bioguide_id": "N000147", "politician_name": "Eleanor Holmes Norton", "ticker": "", "asset_name": "DISTRICT OF COLUMBIA", "transaction_type": "sale", "transaction_date": "2024-05-13", "disclosure_date": "", "amount_display": "50K\u2013100K", "owner": "Undisclosed", "price_at_trade": null, "price_current": null, "return_pct": null, "party": "D", "chamber": "house", "state": "DC", "photo_url": "https://bioguide.congress.gov/bioguide/photo/N/N000147.jpg", "in_office": 1}, {"id": 110348, "bioguide_id": "N000147", "politician_name": "Eleanor Holmes Norton", "ticker": "BRK/B", "asset_name": "Berkshire Hathaway Inc", "transaction_type": "sale", "transaction_date": "2024-04-04", "disclosure_date": "2024-04-17", "amount_display": "1K\u201315K", "owner": "Undisclosed", "price_at_trade": null, "price_current": null, "return_pct": null, "party": "D", "chamber": "house", "state": "DC", "photo_url": "https://bioguide.congress.gov/bioguide/photo/N/N000147.jpg", "in_office": 1}, {"id": 86491, "bioguide_id": "N000147", "politician_name": "Eleanor Holmes Norton", "ticker": "B", "asset_name": "Berkshire Hathaway IncBRK/", "transaction_type": "sale", "transaction_date": "2024-04-04", "disclosure_date": "", "amount_display": "1K\u201315K", "owner": "Undisclosed", "price_at_trade": null, "price_current": null, "return_pct": null, "party": "D", "chamber": "house", "state": "DC", "photo_url": "https://bioguide.congress.gov/bioguide/photo/N/N000147.jpg", "in_office": 1}, {"id": 112595, "bioguide_id": "N000147", "politician_name": "Eleanor Holmes Norton", "ticker": "", "asset_name": "METRO WASHINGTON AIRPORTS AUTH DC", "transaction_type": "sale", "transaction_date": "2023-12-21", "disclosure_date": "2023-12-29", "amount_display": "15K\u201350K", "owner": "Undisclosed", "price_at_trade": null, "price_current": null, "return_pct": null, "party": "D", "chamber": "house", "state": "DC", "photo_url": "https://bioguide.congress.gov/bioguide/photo/N/N000147.jpg", "in_office": 1}, {"id": 114781, "bioguide_id": "N000147", "politician_name": "Eleanor Holmes Norton", "ticker": "", "asset_name": "VIRGINIA RESOURCES AUTHORITY", "transaction_type": "sale", "transaction_date": "2023-10-13", "disclosure_date": "2023-10-25", "amount_display": "15K\u201350K", "owner": "Undisclosed", "price_at_trade": null, "price_current": null, "return_pct": null, "party": "D", "chamber": "house", "state": "DC", "photo_url": "https://bioguide.congress.gov/bioguide/photo/N/N000147.jpg", "in_office": 1}, {"id": 117807, "bioguide_id": "N000147", "politician_name": "Eleanor Holmes Norton", "ticker": "", "asset_name": "STATE OF WASHINGTON", "transaction_type": "sale", "transaction_date": "2023-06-01", "disclosure_date": "2023-07-13", "amount_display": "15K\u201350K", "owner": "Undisclosed", "price_at_trade": null, "price_current": null, "return_pct": null, "party": "D", "chamber": "house", "state": "DC", "photo_url": "https://bioguide.congress.gov/bioguide/photo/N/N000147.jpg", "in_office": 1}, {"id": 120755, "bioguide_id": "N000147", "politician_name": "Eleanor Holmes Norton", "ticker": "", "asset_name": "NATIONAL PUBLIC RADIO INC", "transaction_type": "sale", "transaction_date": "2023-04-03", "disclosure_date": "2023-05-06", "amount_display": "50K\u2013100K", "owner": "Undisclosed", "price_at_trade": null, "price_current": null, "return_pct": null, "party": "D", "chamber": "house", "state": "DC", "photo_url": "https://bioguide.congress.gov/bioguide/photo/N/N000147.jpg", "in_office": 1}]